bincode/__init__.py
bincode/app.py
bincode/static/data.json
bincode-1.1.0.dist-info/LICENSE
bincode-1.1.0.dist-info/METADATA
bincode-1.1.0.dist-info/WHEEL
bincode-1.1.0.dist-info/entry_points.txt
bincode-1.1.0.dist-info/top_level.txt
bincode-1.1.0.dist-info/RECORD
