Metadata-Version: 2.1
Name: bincode
Version: 1.1.0
Summary: To check the validity of a credit/debit card.
Author-email: joumaico <joumaico@gmx.com>
License: MIT License
Project-URL: Homepage, https://github.com/joumaico/bincode
Classifier: License :: OSI Approved :: MIT License
Classifier: Programming Language :: Python
Classifier: Programming Language :: Python :: 3
Requires-Python: >=3.9
License-File: LICENSE
